{
  "system": {
    "language": "zh",
    "fallback_language": "en"
  },
  "camera": {
    "default_camera_id": null,
    "min_fps": 20,
    "detection_confidence": 0.5
  },
  "timeouts": {
    "idle_to_scene_select_seconds": 7,
    "scene_select_inactivity_seconds": 20,
    "motion_capture_inactivity_seconds": 15,
    "final_result_auto_reset_seconds": 60,
    "exit_gesture_duration_seconds": 300,
    "exit_confirmation_duration_seconds": 2
  },
  "storage": {
    "mode": "local",
    "local_path": "data/test_complete",
    "s3_bucket": "",
    "s3_region": "",
    "s3_access_key": "",
    "s3_secret_key": "",
    "max_age_days": 7,
    "min_disk_space_gb": 5,
    "emergency_cleanup_threshold_gb": 2,
    "emergency_cleanup_target_gb": 3
  },
  "rendering": {
    "target_fps": 25,
    "video_codec": "H264",
    "max_render_time_seconds": 30
  },
  "qr_code": {
    "auto_detect_ip": false,
    "manual_ip": "192.168.1.200",
    "port": 8080
  },
  "interaction": {
    "hover_selection_duration_seconds": 5,
    "countdown_duration_seconds": 5,
    "cursor_latency_ms": 100,
    "state_transition_max_ms": 1000
  },
  "api": {
    "retry_attempts": 3,
    "retry_backoff_base_ms": 1000,
    "polling_interval_ms": 2000
  }
}



